{
    "SMT": {
        "time": 1.495,
        "optimal": true,
        "obj": 220,
        "sol": [
            [
                2
            ],
            [
                6
            ],
            [
                0
            ],
            [
                5
            ],
            [
                4
            ],
            [
                7
            ],
            [
                3,
                1,
                8
            ],
            [
                9
            ]
        ]
    }
}